CHANGELOG.md
LICENSE
MANIFEST.in
README.md
setup.cfg
setup.py
convert/ArrayConverter.py
convert/BooleanConverter.py
convert/DateTimeConverter.py
convert/DoubleConverter.py
convert/FloatConverter.py
convert/IntegerConverter.py
convert/JsonConverter.py
convert/LongConverter.py
convert/MapConverter.py
convert/RecursiveMapConverter.py
convert/StringConverter.py
convert/TypeCode.py
convert/TypeConverter.py
convert/UTC.py
convert/__init__.py
pip_services3_commons/__init__.py
pip_services3_commons.egg-info/PKG-INFO
pip_services3_commons.egg-info/SOURCES.txt
pip_services3_commons.egg-info/dependency_links.txt
pip_services3_commons.egg-info/requires.txt
pip_services3_commons.egg-info/top_level.txt
pip_services3_commons.egg-info/zip-safe
pip_services3_commons/commands/Command.py
pip_services3_commons/commands/CommandSet.py
pip_services3_commons/commands/Event.py
pip_services3_commons/commands/ICommand.py
pip_services3_commons/commands/ICommandInterceptor.py
pip_services3_commons/commands/ICommandable.py
pip_services3_commons/commands/IEvent.py
pip_services3_commons/commands/IEventListener.py
pip_services3_commons/commands/InterceptedCommand.py
pip_services3_commons/commands/__init__.py
pip_services3_commons/config/ConfigParams.py
pip_services3_commons/config/IConfigurable.py
pip_services3_commons/config/IReconfigurable.py
pip_services3_commons/config/NameResolver.py
pip_services3_commons/config/OptionsResolver.py
pip_services3_commons/config/__init__.py
pip_services3_commons/convert/ArrayConverter.py
pip_services3_commons/convert/BooleanConverter.py
pip_services3_commons/convert/DateTimeConverter.py
pip_services3_commons/convert/DoubleConverter.py
pip_services3_commons/convert/FloatConverter.py
pip_services3_commons/convert/IntegerConverter.py
pip_services3_commons/convert/JsonConverter.py
pip_services3_commons/convert/LongConverter.py
pip_services3_commons/convert/MapConverter.py
pip_services3_commons/convert/RecursiveMapConverter.py
pip_services3_commons/convert/StringConverter.py
pip_services3_commons/convert/TypeCode.py
pip_services3_commons/convert/TypeConverter.py
pip_services3_commons/convert/UTC.py
pip_services3_commons/convert/__init__.py
pip_services3_commons/data/AnyValue.py
pip_services3_commons/data/AnyValueArray.py
